core/__init__.py
core/base.py
mcp_server_public_transport-0.1.2.dist-info/licenses/LICENSE
mcp_server_public_transport-0.1.2.dist-info/METADATA
mcp_server_public_transport-0.1.2.dist-info/WHEEL
mcp_server_public_transport-0.1.2.dist-info/top_level.txt
mcp_server_public_transport-0.1.2.dist-info/RECORD
