Metadata-Version: 2.4
Name: mcp-server-public-transport
Version: 0.1.2
Summary: An MCP-compatible server for querying public transport data in Europe (UK, CH, BE, NO).
Author-email: Miro Duman <dumanmiro@gmail.com>
License: MIT
Project-URL: Homepage, https://github.com/mirodn/mcp-server-public-transport
Project-URL: Repository, https://github.com/mirodn/mcp-server-public-transport
Keywords: mcp,public transport,api,europe,fastmcp
Classifier: Development Status :: 2 - Pre-Alpha
Classifier: Intended Audience :: Developers
Classifier: License :: OSI Approved :: MIT License
Classifier: Programming Language :: Python :: 3.11
Classifier: Topic :: Software Development :: Libraries
Requires-Python: >=3.11
License-File: LICENSE
Requires-Dist: aiohttp>=3.12.14
Requires-Dist: certifi>=2025.7.14
Requires-Dist: fastmcp>=2.10.6
Requires-Dist: python-dotenv>=1.1.1
Requires-Dist: requests>=2.32.4
Provides-Extra: dev
Requires-Dist: pytest>=8.4.1; extra == "dev"
Requires-Dist: pytest-asyncio>=1.1.0; extra == "dev"
Requires-Dist: ruff>=0.4.5; extra == "dev"
Dynamic: license-file
